collectivo/__init__.py
collectivo/apps.py
collectivo/errors.py
collectivo/models.py
collectivo/routers.py
collectivo/urls.py
collectivo/utils.py
collectivo/version.py
collectivo/views.py
collectivo/auth/__init__.py
collectivo/auth/apps.py
collectivo/auth/clients.py
collectivo/auth/manager.py
collectivo/auth/middleware.py
collectivo/auth/models.py
collectivo/auth/permissions.py
collectivo/auth/populate.py
collectivo/auth/serializers.py
collectivo/auth/urls.py
collectivo/auth/userinfo.py
collectivo/auth/views.py
collectivo/auth/tests/__init__.py
collectivo/auth/tests/test_auth.py
collectivo/auth/tests/test_registration.py
collectivo/dashboard/__init__.py
collectivo/dashboard/apps.py
collectivo/dashboard/models.py
collectivo/dashboard/serializers.py
collectivo/dashboard/tests.py
collectivo/dashboard/urls.py
collectivo/dashboard/utils.py
collectivo/dashboard/views.py
collectivo/dashboard/migrations/0001_initial.py
collectivo/dashboard/migrations/__init__.py
collectivo/extension_template/__init__.py
collectivo/extension_template/apps.py
collectivo/extension_template/models.py
collectivo/extension_template/serializers.py
collectivo/extension_template/urls.py
collectivo/extension_template/views.py
collectivo/extension_template/migrations/__init__.py
collectivo/extensions/__init__.py
collectivo/extensions/apps.py
collectivo/extensions/models.py
collectivo/extensions/serializers.py
collectivo/extensions/tests.py
collectivo/extensions/urls.py
collectivo/extensions/utils.py
collectivo/extensions/views.py
collectivo/extensions/migrations/0001_initial.py
collectivo/extensions/migrations/__init__.py
collectivo/members/__init__.py
collectivo/members/apps.py
collectivo/members/models.py
collectivo/members/permissions.py
collectivo/members/serializers.py
collectivo/members/urls.py
collectivo/members/views.py
collectivo/members/migrations/0001_initial.py
collectivo/members/migrations/0002_alter_member_email_verified.py
collectivo/members/migrations/__init__.py
collectivo-0.0.3.dist-info/LICENSE
collectivo-0.0.3.dist-info/METADATA
collectivo-0.0.3.dist-info/WHEEL
collectivo-0.0.3.dist-info/top_level.txt
collectivo-0.0.3.dist-info/RECORD
